emailbuilder/__init__.py
emailbuilder/email.py
emailbuilder/experimental.py
emailbuilder/utils.py
emailbuilder/components/__init__.py
emailbuilder/components/base.py
emailbuilder/components/containers.py
emailbuilder/components/elements.py
emailbuilder/components/embeddables.py
emailbuilder-0.1.4.dist-info/METADATA
emailbuilder-0.1.4.dist-info/WHEEL
emailbuilder-0.1.4.dist-info/top_level.txt
emailbuilder-0.1.4.dist-info/RECORD
