Metadata-Version: 2.1
Name: emailbuilder
Version: 0.1.4
Summary: Simple HTML e-mail generator
Home-page: https://github.com/coheleth/emailbuilder
Author: Coheleth
Author-email: Diogo Silva <diogopiccirillo@gmail.com>
License: MIT
Project-URL: homepage, https://github.com/coheleth/emailbuilder
Project-URL: documentation, https://github.com/coheleth/emailbuilder
Project-URL: repository, https://github.com/coheleth/emailbuilder
Requires-Python: >=3.7
